sanitongo/__init__.py
sanitongo/config.py
sanitongo/exceptions.py
sanitongo/layers.py
sanitongo/py.typed
sanitongo/sanitizer.py
sanitongo/schema.py
sanitongo-0.1.3.dist-info/METADATA
sanitongo-0.1.3.dist-info/WHEEL
sanitongo-0.1.3.dist-info/licenses/LICENSE
sanitongo-0.1.3.dist-info/RECORD
