Metadata-Version: 2.4
Name: sanitongo
Version: 0.1.3
Summary: Modern MongoDB query sanitizer with layered security protection
Project-URL: Homepage, https://github.com/izikeros/sanitongo
Project-URL: Documentation, https://izikeros.github.io/sanitongo
Project-URL: Repository, https://github.com/izikeros/sanitongo
Project-URL: Bug Tracker, https://github.com/izikeros/sanitongo/issues
Project-URL: Changelog, https://github.com/izikeros/sanitongo/blob/main/CHANGELOG.md
Author-email: Krystian Safjan <ksafjan@gmail.com>
Maintainer-email: Krystian Safjan <ksafjan@gmail.com>
License: MIT License
License-File: LICENSE
Keywords: injection,mongodb,nosql,sanitizer,security
Classifier: Development Status :: 4 - Beta
Classifier: Intended Audience :: Developers
Classifier: License :: OSI Approved :: MIT License
Classifier: Operating System :: OS Independent
Classifier: Programming Language :: Python :: 3
Classifier: Programming Language :: Python :: 3.10
Classifier: Programming Language :: Python :: 3.11
Classifier: Programming Language :: Python :: 3.12
Classifier: Programming Language :: Python :: 3.13
Classifier: Topic :: Database
Classifier: Topic :: Security
Classifier: Topic :: Software Development :: Libraries :: Python Modules
Classifier: Typing :: Typed
Requires-Python: >=3.10
Requires-Dist: pydantic>=2.0.0
Requires-Dist: typing-extensions>=4.0.0
